LICENSE
README.md
setup.cfg
setup.py
google_drive_data_transfer/GoogleDriveDataTransfer.py
google_drive_data_transfer/__init__.py
google_drive_data_transfer.egg-info/PKG-INFO
google_drive_data_transfer.egg-info/SOURCES.txt
google_drive_data_transfer.egg-info/dependency_links.txt
google_drive_data_transfer.egg-info/not-zip-safe
google_drive_data_transfer.egg-info/requires.txt
google_drive_data_transfer.egg-info/top_level.txt