Metadata-Version: 1.0
Name: google-drive-data-transfer
Version: 0.1
Summary: Basic file management on Google Drive
Home-page: https://github.com/frederik-schmidt/google_drive_data_transfer
Author: Frederik Schmidt
Author-email: UNKNOWN
License: MIT
Platform: UNKNOWN
